Redy/Typing.py
Redy/__init__.py
Redy/settings.py
Redy/ADT/Core.py
Redy/ADT/__init__.py
Redy/ADT/traits.py
Redy/Async/Accompany.py
Redy/Async/Delegate.py
Redy/Async/__init__.py
Redy/Async/traits.py
Redy/Collections/Core.py
Redy/Collections/Graph.py
Redy/Collections/LinkedList.py
Redy/Collections/Traversal.py
Redy/Collections/__init__.py
Redy/Magic/Classic.py
Redy/Magic/Pattern.py
Redy/Magic/__init__.py
Redy/Opt/ConstExpr.py
Redy/Opt/Feature.py
Redy/Opt/__init__.py
Redy/Opt/basic.py
Redy/Opt/bytecode_api.py
Redy/Opt/utils.py
Redy/Opt/builtin_features/__init__.py
Redy/Opt/builtin_features/_as_store.py
Redy/Opt/builtin_features/_constant_link.py
Redy/Opt/builtin_features/_constexpr.py
Redy/Opt/builtin_features/_goto.py
Redy/Opt/builtin_features/_macro.py
Redy/Opt/builtin_features/common.py
Redy/Tools/Hash.py
Redy/Tools/PathLib.py
Redy/Tools/TypeInterface.py
Redy/Tools/Version.py
Redy/Tools/__init__.py
Redy/Tools/_native_hash.py
Redy/Tools/_py_hash.py
Redy-0.2.10.dist-info/METADATA
Redy-0.2.10.dist-info/RECORD
Redy-0.2.10.dist-info/WHEEL
Redy-0.2.10.dist-info/top_level.txt
