Metadata-Version: 2.1
Name: Redy
Version: 0.2.10
Summary: an integrated library for module python
Home-page: https://github.com/thautwarm/Redy
Author: thautwarm
Author-email: twshere@outlook.com
License: MIT
Keywords: python solution
Platform: any
Classifier: Programming Language :: Python :: 3.6
Classifier: Programming Language :: Python :: 3.7
Classifier: Programming Language :: Python :: Implementation :: CPython
Requires-Dist: bytecode (>=0.7)
